s3_memoize/__init__.py
s3_memoize/s3_memoize.py
s3_memoize-0.1.4.dist-info/LICENSE
s3_memoize-0.1.4.dist-info/METADATA
s3_memoize-0.1.4.dist-info/WHEEL
s3_memoize-0.1.4.dist-info/top_level.txt
s3_memoize-0.1.4.dist-info/RECORD
